scale_align/__init__.py
scale_align/aligner.py
scale_align/cli.py
scale_align/embeddings.py
scale_align/io.py
scale_align/retrieval.py
scale_align/selection.py
scale_align-0.1.1.dist-info/METADATA
scale_align-0.1.1.dist-info/WHEEL
scale_align-0.1.1.dist-info/entry_points.txt
scale_align-0.1.1.dist-info/licenses/LICENSE
scale_align-0.1.1.dist-info/RECORD
