Metadata-Version: 2.4
Name: scale-align
Version: 0.1.1
Summary: Standard Classification Alignment & Local Enrichment - Automate audit and enrichment of industrial classifications
Project-URL: Homepage, https://github.com/mdmahendri/scale-align
Project-URL: Repository, https://github.com/mdmahendri/scale-align
Author-email: Mahendri Dwicahyo <mahendri.md@gmail.com>
License-Expression: MIT
License-File: LICENSE
Keywords: alignment,classification,embeddings,isic,nace,retrieval
Classifier: Development Status :: 3 - Alpha
Classifier: Intended Audience :: Developers
Classifier: License :: OSI Approved :: MIT License
Classifier: Programming Language :: Python :: 3
Classifier: Programming Language :: Python :: 3.9
Classifier: Programming Language :: Python :: 3.10
Classifier: Programming Language :: Python :: 3.11
Classifier: Programming Language :: Python :: 3.12
Classifier: Topic :: Scientific/Engineering :: Information Analysis
Requires-Python: >=3.9
Requires-Dist: click>=8.0.0
Requires-Dist: numpy>=1.24.0
Requires-Dist: torch>=2.0.0
Requires-Dist: transformers>=4.30.0
Provides-Extra: dev
Requires-Dist: pytest-cov>=4.0.0; extra == 'dev'
Requires-Dist: pytest>=7.0.0; extra == 'dev'
